{"stats":{"minecraft:dropped":{"minecraft:quartz_slab":1},"minecraft:picked_up":{"minecraft:quartz_slab":1,"minecraft:stone":1,"minecraft:torch":1,"minecraft:oak_button":1,"minecraft:netherrack":905,"minecraft:cobblestone":42},"minecraft:mined":{"minecraft:cobblestone":60,"minecraft:stone":1,"minecraft:netherrack":1139},"minecraft:custom":{"minecraft:time_since_rest":15034,"minecraft:play_one_minute":15034,"minecraft:crouch_one_cm":22606,"minecraft:sprint_one_cm":44332,"minecraft:damage_taken":16,"minecraft:walk_one_cm":74396,"minecraft:sneak_time":3933,"minecraft:drop":1,"minecraft:aviate_one_cm":7427,"minecraft:jump":251,"minecraft:leave_game":1,"minecraft:time_since_death":15034,"minecraft:fly_one_cm":38054,"minecraft:fall_one_cm":4083},"minecraft:used":{"minecraft:cooked_chicken":3,"minecraft:netherrack":690,"minecraft:torch":3,"minecraft:diamond_pickaxe":1200}},"DataVersion":1976}